aiohttp_mako/__init__.py
aiohttp_mako-0.4.0.dist-info/LICENSE
aiohttp_mako-0.4.0.dist-info/METADATA
aiohttp_mako-0.4.0.dist-info/WHEEL
aiohttp_mako-0.4.0.dist-info/top_level.txt
aiohttp_mako-0.4.0.dist-info/RECORD
