Metadata-Version: 2.1
Name: aiohttp-mako
Version: 0.4.0
Summary: mako template renderer for aiohttp.web (http server for asyncio)
Home-page: https://github.com/aio-libs/aiohttp-mako/
Author: Nikolay Novik
Author-email: nickolainovik@gmail.com
License: Apache 2
Platform: UNKNOWN
Classifier: License :: OSI Approved :: Apache Software License
Classifier: Intended Audience :: Developers
Classifier: Programming Language :: Python
Classifier: Programming Language :: Python :: 3
Classifier: Programming Language :: Python :: 3.5
Classifier: Programming Language :: Python :: 3.6
Classifier: Programming Language :: Python :: 3.7
Classifier: Topic :: Internet :: WWW/HTTP
Classifier: Framework :: AsyncIO
Requires-Python: >=3.5.3
Requires-Dist: aiohttp (>=3.0)
Requires-Dist: mako (>=1.0.0)
